Metadata-Version: 2.1
Name: ControlCharts
Version: 1.0.0
Summary: Control charts for process monitoring and anomaly detection
Home-page: https://github.com/YKatser/ControlCharts
Author: Iurii Katser
Author-email: waico@waico.ru
License: MIT
Platform: UNKNOWN
License-File: LICENSE
